invenio_oauthclient_aaf/__init__.py
invenio_oauthclient_aaf/handlers.py
invenio_oauthclient_aaf/remote.py
invenio_oauthclient_aaf-0.2.0.dist-info/licenses/LICENSE
invenio_oauthclient_aaf-0.2.0.dist-info/METADATA
invenio_oauthclient_aaf-0.2.0.dist-info/WHEEL
invenio_oauthclient_aaf-0.2.0.dist-info/entry_points.txt
invenio_oauthclient_aaf-0.2.0.dist-info/top_level.txt
invenio_oauthclient_aaf-0.2.0.dist-info/RECORD
