Metadata-Version: 2.4
Name: invenio-oauthclient-aaf
Version: 0.2.0
Summary: AAF (Australian Access Federation) OAuth integration for InvenioRDM
Author-email: Bata Byambasuren <bata.byambasuren@adelaide.edu.au>
License: MIT
Project-URL: Homepage, https://github.com/aus-plant-phenomics-network/invenio-oauthclient-aaf
Project-URL: Documentation, https://github.com/aus-plant-phenomics-network/invenio-oauthclient-aaf/blob/main/README.md
Project-URL: Repository, https://github.com/aus-plant-phenomics-network/invenio-oauthclient-aaf
Project-URL: Issues, https://github.com/aus-plant-phenomics-network/invenio-oauthclient-aaf/issues
Keywords: invenio,oauth,aaf,openid-connect,authentication
Classifier: Intended Audience :: Developers
Classifier: License :: OSI Approved :: MIT License
Classifier: Operating System :: OS Independent
Classifier: Programming Language :: Python :: 3
Classifier: Programming Language :: Python :: 3.9
Classifier: Programming Language :: Python :: 3.10
Classifier: Programming Language :: Python :: 3.11
Classifier: Programming Language :: Python :: 3.12
Classifier: Topic :: Internet :: WWW/HTTP :: Dynamic Content
Requires-Python: >=3.9
License-File: LICENSE
Requires-Dist: invenio-oauthclient>=2.0.0
Provides-Extra: tests
Requires-Dist: pytest>=7.0.0; extra == "tests"
Requires-Dist: pytest-cov>=4.0.0; extra == "tests"
Requires-Dist: pytest-mock>=3.10.0; extra == "tests"
Requires-Dist: pytest-flask>=1.2.0; extra == "tests"
Provides-Extra: dev
Requires-Dist: ruff>=0.14.0; extra == "dev"
Requires-Dist: pre-commit>=4.3.0; extra == "dev"
Requires-Dist: pytest>=7.0.0; extra == "dev"
Requires-Dist: pytest-cov>=4.0.0; extra == "dev"
Requires-Dist: pytest-mock>=3.10.0; extra == "dev"
Requires-Dist: pytest-flask>=1.2.0; extra == "dev"
Requires-Dist: mypy>=0.0.1; extra == "dev"
Requires-Dist: python-semantic-release>=9.0.0; extra == "dev"
Requires-Dist: commitizen>=3.0.0; extra == "dev"
Requires-Dist: ipython>=8.0.0; extra == "dev"
Requires-Dist: ipdb>=0.13.0; extra == "dev"
Provides-Extra: docs
Requires-Dist: sphinx>=5.0.0; extra == "docs"
Requires-Dist: sphinx-rtd-theme>=1.2.0; extra == "docs"
Dynamic: license-file
